pdoc/__init__.py
pdoc/__main__.py
pdoc/_compat.py
pdoc/doc.py
pdoc/doc_ast.py
pdoc/doc_pyi.py
pdoc/doc_types.py
pdoc/docstrings.py
pdoc/extract.py
pdoc/py.typed
pdoc/render.py
pdoc/render_helpers.py
pdoc/search.py
pdoc/web.py
pdoc/markdown2/LICENSE
pdoc/markdown2/README.md
pdoc/markdown2/__init__.py
pdoc/templates/README.md
pdoc/templates/build-search-index.js
pdoc/templates/content.css
pdoc/templates/custom.css
pdoc/templates/layout.css
pdoc/templates/livereload.html.jinja2
pdoc/templates/math.html.jinja2
pdoc/templates/mermaid.html.jinja2
pdoc/templates/search.html.jinja2
pdoc/templates/search.js.jinja2
pdoc/templates/syntax-highlighting.css
pdoc/templates/theme.css
pdoc/templates/default/error.html.jinja2
pdoc/templates/default/frame.html.jinja2
pdoc/templates/default/index.html.jinja2
pdoc/templates/default/module.html.jinja2
pdoc/templates/deprecated/README.md
pdoc/templates/deprecated/bootstrap-reboot.min.css
pdoc/templates/deprecated/box-arrow-in-left.svg
pdoc/templates/deprecated/elasticlunr.min.js
pdoc/templates/deprecated/favicon.svg
pdoc/templates/deprecated/navtoggle.svg
pdoc/templates/deprecated/pdoc-logo.svg
pdoc/templates/deprecated/resources/favicon.svg
pdoc/templates/resources/bootstrap-reboot.min.css
pdoc/templates/resources/box-arrow-in-left.svg
pdoc/templates/resources/elasticlunr.min.js
pdoc/templates/resources/exclamation-octagon-fill.svg
pdoc/templates/resources/exclamation-square-fill.svg
pdoc/templates/resources/exclamation-triangle-fill.svg
pdoc/templates/resources/info-circle-fill.svg
pdoc/templates/resources/lightbulb.svg
pdoc/templates/resources/lightning-fill.svg
pdoc/templates/resources/navtoggle.svg
pdoc/templates/resources/pdoc-logo.svg
pdoc-15.0.3.dist-info/LICENSE
pdoc-15.0.3.dist-info/METADATA
pdoc-15.0.3.dist-info/WHEEL
pdoc-15.0.3.dist-info/entry_points.txt
pdoc-15.0.3.dist-info/top_level.txt
pdoc-15.0.3.dist-info/RECORD
