Metadata-Version: 2.1
Name: pdoc
Version: 15.0.3
Summary: API Documentation for Python Projects
Author-email: Maximilian Hils <pdoc@maximilianhils.com>
License: MIT-0
Project-URL: Homepage, https://pdoc.dev
Project-URL: Source, https://github.com/mitmproxy/pdoc/
Project-URL: Documentation, https://pdoc.dev/docs/pdoc.html
Project-URL: Issues, https://github.com/mitmproxy/pdoc/issues
Classifier: Topic :: Documentation
Classifier: Topic :: Software Development :: Documentation
Classifier: Topic :: Utilities
Classifier: License :: Public Domain
Classifier: Development Status :: 5 - Production/Stable
Classifier: Environment :: Console
Classifier: Intended Audience :: Developers
Classifier: Operating System :: OS Independent
Classifier: Programming Language :: Python :: 3.9
Classifier: Programming Language :: Python :: 3.10
Classifier: Programming Language :: Python :: 3.11
Classifier: Programming Language :: Python :: 3.12
Classifier: Programming Language :: Python :: 3.13
Classifier: Typing :: Typed
Requires-Python: >=3.9
License-File: LICENSE
Requires-Dist: Jinja2>=2.11.0
Requires-Dist: pygments>=2.12.0
Requires-Dist: MarkupSafe>=1.1.1
